fluxlib/__init__.py
fluxlib/ustar_filtering.py
fluxlib/gapfill/__init__.py
fluxlib/gapfill/auxfill_xgb.py
fluxlib/gapfill/dataloader.py
fluxlib/gapfill/gapfill_routine.py
fluxlib/gapfill/ggapfill.py
fluxlib/gapfill/hesse_flux_mds_gapfill.py
fluxlib/gapfill/utils.py
fluxlib/partitioning/__init__.py
fluxlib/partitioning/mad.py
fluxlib/partitioning/nee2gpp.py
fluxlib/partitioning/partitioning.py
fluxlib/partitioning/const/__init__.py
fluxlib/partitioning/const/const.py
fluxlib/partitioning/functions/__init__.py
fluxlib/partitioning/functions/fit_functions.py
fluxlib/partitioning/functions/general_functions.py
fluxlib/partitioning/functions/logistic_function.py
fluxlib/partitioning/functions/opti_test_functions.py
fluxlib/partitioning/functions/sa_test_functions.py
fluxlib/preprocessing/__init__.py
fluxlib/preprocessing/formatize.py
fluxlib/preprocessing/share_drivers.py
fluxlib/toolbox/__init__.py
fluxlib/toolbox/auxdata.py
fluxlib/toolbox/fluxnet.py
fluxlib/toolbox/funcs.py
fluxlib/toolbox/run_fluxnet_example.py
fluxlib-0.0.29.dist-info/METADATA
fluxlib-0.0.29.dist-info/WHEEL
fluxlib-0.0.29.dist-info/top_level.txt
fluxlib-0.0.29.dist-info/RECORD
