Metadata-Version: 2.1
Name: fluxlib
Version: 0.0.29
Summary: fluxlib is a package for eddy covariance post-processing
Home-page: https://github.com/soonyenju/fluxlib
Author: Songyan Zhu
Author-email: sz394@exeter.ac.uk
License: MIT Licence
Keywords: eddy covariance,flux,gap-filling
Platform: any
